morphr/__init__.py
morphr/cli.py
morphr/configuration.py
morphr/logging.py
morphr/objectives/iga_membrane_3p_ad.py
morphr/objectives/iga_normal_distance_ad.py
morphr/objectives/iga_point_distance_ad.py
morphr/objectives/iga_point_location_ad.py
morphr/objectives/iga_point_node_coupling_ad.py
morphr/objectives/iga_rotation_coupling_ad.py
morphr/objectives/iga_shell_3p_ad.py
morphr/objectives/reduced_shell.py
morphr/objectives/utility.py
morphr/tasks/apply_alpha_regularization.py
morphr/tasks/apply_edge_coupling.py
morphr/tasks/apply_membrane_3p.py
morphr/tasks/apply_mesh_displacement.py
morphr/tasks/apply_multiple_knot_coupling.py
morphr/tasks/apply_reduced_shell.py
morphr/tasks/apply_shell_3p.py
morphr/tasks/export_ibra.py
morphr/tasks/export_mdpa.py
morphr/tasks/import_displacement_field.py
morphr/tasks/import_ibra.py
morphr/tasks/solve_nonlinear.py
morphr/tests/test_app.py
morphr/tests/test_normal_distance.py
morphr/tests/test_point_distance.py
morphr/tests/test_point_location.py
morphr/tests/test_point_node_coupling.py
morphr/tests/test_rotation_coupling.py
morphr/tests/test_shell_3p.py
morphr-0.6.0.dist-info/LICENSE
morphr-0.6.0.dist-info/METADATA
morphr-0.6.0.dist-info/WHEEL
morphr-0.6.0.dist-info/entry_points.txt
morphr-0.6.0.dist-info/top_level.txt
morphr-0.6.0.dist-info/RECORD
