Metadata-Version: 2.1
Name: morphr
Version: 0.6.0
Summary: UNKNOWN
Home-page: UNKNOWN
Author: Thomas Oberbichler
Author-email: thomas.oberbichler@tum.de
License: UNKNOWN
Platform: UNKNOWN
Requires-Dist: anurbs (==0.14.0)
Requires-Dist: colorama (==0.4.3)
Requires-Dist: click (==7.1.2)
Requires-Dist: eqlib (==0.37.1)
Requires-Dist: hyperjet (==0.35.0)
Requires-Dist: meshio (==4.0.16)
Requires-Dist: numpy (==1.19.0)
Requires-Dist: pydantic (==1.5.1)
